intertech_psu/__init__.py
intertech_psu/example.py
intertech_pdu_lightning1-0.0.1.dist-info/LICENSE
intertech_pdu_lightning1-0.0.1.dist-info/METADATA
intertech_pdu_lightning1-0.0.1.dist-info/WHEEL
intertech_pdu_lightning1-0.0.1.dist-info/top_level.txt
intertech_pdu_lightning1-0.0.1.dist-info/RECORD
