Metadata-Version: 2.1
Name: intertech-pdu-lightning1
Version: 0.0.1
Summary: Intertech PDU
Home-page: https://github.com/lightning1/intertech_pdu
Author: Felix
Author-email: f.kluge@agdsn.de
License: UNKNOWN
Project-URL: Bug Tracker, https://github.com/lightning1/intertech_pdu/issues
Platform: UNKNOWN
Classifier: Programming Language :: Python :: 3
Classifier: License :: OSI Approved :: MIT License
Classifier: Operating System :: OS Independent
Requires-Python: >=3.6
License-File: LICENSE
